<?xml version="1.0" encoding="UTF-8"?>
<!DOCTYPE plist PUBLIC "-//Apple Computer//DTD PLIST 1.0//EN" "http://www.apple.com/DTDs/PropertyList-1.0.dtd">
<plist version="1.0">
<dict>
	<key>Major Version</key><integer>1</integer>
	<key>Minor Version</key><integer>1</integer>
	<key>Date</key><date>2025-06-04T02:46:42Z</date>
	<key>Application Version</key><string>12.13.7.1</string>
	<key>Features</key><integer>5</integer>
	<key>Show Content Ratings</key><true/>
	<key>Music Folder</key><string>file://localhost/E:/Users/aldol/Music/iTunes/iTunes%20Media/</string>
	<key>Library Persistent ID</key><string>187AD5E35C5E82C1</string>
	<key>Tracks</key>
	<dict>
		<key>2790</key>
		<dict>
			<key>Track ID</key><integer>2790</integer>
			<key>Name</key><string>Installing the Catheter</string>
			<key>Artist</key><string>36 Crazyfists</string>
			<key>Composer</key><string>Brock Lindow/Steve Holt/Thomas Noonan</string>
			<key>Album</key><string>A Snow Capped Romance</string>
			<key>Genre</key><string>New Metal</string>
			<key>Kind</key><string>MPEG audio file</string>
			<key>Size</key><integer>5623992</integer>
			<key>Total Time</key><integer>231627</integer>
			<key>Track Number</key><integer>9</integer>
			<key>Year</key><integer>2004</integer>
			<key>Date Modified</key><date>2023-09-30T00:31:37Z</date>
			<key>Date Added</key><date>2025-05-22T23:54:52Z</date>
			<key>Bit Rate</key><integer>192</integer>
			<key>Sample Rate</key><integer>44100</integer>
			<key>Volume Adjustment</key><integer>106</integer>
			<key>Comments</key><string> 00001044 00000EB1 00005CE9 00005A24 0001D4D7 0000C395 00008000 00008000 0000C395 0000C395</string>
			<key>Play Count</key><integer>4</integer>
			<key>Play Date</key><integer>3778869912</integer>
			<key>Play Date UTC</key><date>2023-09-30T01:05:12Z</date>
			<key>Normalization</key><integer>4831</integer>
			<key>Artwork Count</key><integer>1</integer>
			<key>Sort Album</key><string>Snow Capped Romance</string>
			<key>Persistent ID</key><string>F2B21FF8E3677619</string>
			<key>Track Type</key><string>File</string>
			<key>Location</key><string>file://localhost/U:/Shared/Music/36%20Crazyfists%20-%20(2004)%20A%20Snow%20Capped%20Romance%20-%20Installing%20the%20Catheter.mp3</string>
			<key>File Folder Count</key><integer>-1</integer>
			<key>Library Folder Count</key><integer>-1</integer>
		</dict>
		<key>3046</key>
		<dict>
			<key>Track ID</key><integer>3046</integer>
			<key>Name</key><string>Celice</string>
			<key>Artist</key><string>A-HA</string>
			<key>Genre</key><string>Pop</string>
			<key>Kind</key><string>MPEG audio file</string>
			<key>Size</key><integer>5931008</integer>
			<key>Total Time</key><integer>209580</integer>
			<key>Track Number</key><integer>39</integer>
			<key>Year</key><integer>2005</integer>
			<key>Date Modified</key><date>2021-09-03T01:09:42Z</date>
			<key>Date Added</key><date>2025-05-22T23:55:04Z</date>
			<key>Bit Rate</key><integer>226</integer>
			<key>Sample Rate</key><integer>44100</integer>
			<key>Comments</key><string> </string>
			<key>Normalization</key><integer>4240</integer>
			<key>Persistent ID</key><string>6C6378E01ED19A23</string>
			<key>Track Type</key><string>File</string>
			<key>Location</key><string>file://localhost/U:/Shared/Music/A-HA%20-%20Celice.mp3</string>
			<key>File Folder Count</key><integer>-1</integer>
			<key>Library Folder Count</key><integer>-1</integer>
		</dict>
		<key>6258</key>
		<dict>
			<key>Track ID</key><integer>6258</integer>
			<key>Name</key><string>Além da Cor</string>
			<key>Artist</key><string>Choldra</string>
			<key>Genre</key><string>Blues</string>
			<key>Kind</key><string>MPEG audio file</string>
			<key>Size</key><integer>4249600</integer>
			<key>Total Time</key><integer>265534</integer>
			<key>Year</key><integer>2005</integer>
			<key>Date Modified</key><date>2021-09-03T02:33:33Z</date>
			<key>Date Added</key><date>2025-05-22T23:58:19Z</date>
			<key>Bit Rate</key><integer>128</integer>
			<key>Sample Rate</key><integer>44100</integer>
			<key>Normalization</key><integer>6925</integer>
			<key>Persistent ID</key><string>0E6879925A6B08CD</string>
			<key>Track Type</key><string>File</string>
			<key>Location</key><string>file://localhost/U:/Shared/Music/Choldra%20-%20Al%C3%A9m%20da%20Cor.mp3</string>
			<key>File Folder Count</key><integer>-1</integer>
			<key>Library Folder Count</key><integer>-1</integer>
		</dict>
		<key>6260</key>
		<dict>
			<key>Track ID</key><integer>6260</integer>
			<key>Name</key><string>Casulo</string>
			<key>Artist</key><string>Choldra</string>
			<key>Album</key><string>Choldra</string>
			<key>Genre</key><string>Blues</string>
			<key>Kind</key><string>MPEG audio file</string>
			<key>Size</key><integer>2826240</integer>
			<key>Total Time</key><integer>176587</integer>
			<key>Year</key><integer>2005</integer>
			<key>Date Modified</key><date>2024-07-04T16:22:27Z</date>
			<key>Date Added</key><date>2025-05-22T23:58:19Z</date>
			<key>Bit Rate</key><integer>128</integer>
			<key>Sample Rate</key><integer>44100</integer>
			<key>Volume Adjustment</key><integer>100</integer>
			<key>Normalization</key><integer>5567</integer>
			<key>Persistent ID</key><string>69936EBC57C43C85</string>
			<key>Track Type</key><string>File</string>
			<key>Location</key><string>file://localhost/U:/Shared/Music/Choldra%20-%20Casulo.mp3</string>
			<key>File Folder Count</key><integer>-1</integer>
			<key>Library Folder Count</key><integer>-1</integer>
		</dict>
		<key>6838</key>
		<dict>
			<key>Track ID</key><integer>6838</integer>
			<key>Name</key><string>Cold</string>
			<key>Artist</key><string>Crossfade</string>
			<key>Album</key><string>Crossfade</string>
			<key>Genre</key><string>Alternative</string>
			<key>Kind</key><string>MPEG audio file</string>
			<key>Size</key><integer>4792817</integer>
			<key>Total Time</key><integer>197485</integer>
			<key>Year</key><integer>2004</integer>
			<key>Date Modified</key><date>2021-09-03T02:47:32Z</date>
			<key>Date Added</key><date>2025-05-22T23:58:47Z</date>
			<key>Bit Rate</key><integer>192</integer>
			<key>Sample Rate</key><integer>44100</integer>
			<key>Play Count</key><integer>1</integer>
			<key>Play Date</key><integer>3676990812</integer>
			<key>Play Date UTC</key><date>2020-07-07T21:20:12Z</date>
			<key>Normalization</key><integer>10386</integer>
			<key>Artwork Count</key><integer>1</integer>
			<key>Persistent ID</key><string>7BFA2E6BEF78142F</string>
			<key>Track Type</key><string>File</string>
			<key>Location</key><string>file://localhost/U:/Shared/Music/Crossfade%20-%20(2004)%20Crossfade%20-%20Cold.mp3</string>
			<key>File Folder Count</key><integer>-1</integer>
			<key>Library Folder Count</key><integer>-1</integer>
		</dict>
		<key>6840</key>
		<dict>
			<key>Track ID</key><integer>6840</integer>
			<key>Name</key><string>Colors</string>
			<key>Artist</key><string>Crossfade</string>
			<key>Album</key><string>Crossfade</string>
			<key>Genre</key><string>Other</string>
			<key>Kind</key><string>MPEG audio file</string>
			<key>Size</key><integer>4836940</integer>
			<key>Total Time</key><integer>199314</integer>
			<key>Year</key><integer>2004</integer>
			<key>Date Modified</key><date>2021-09-03T02:47:35Z</date>
			<key>Date Added</key><date>2025-05-22T23:58:47Z</date>
			<key>Bit Rate</key><integer>192</integer>
			<key>Sample Rate</key><integer>44100</integer>
			<key>Normalization</key><integer>6053</integer>
			<key>Artwork Count</key><integer>1</integer>
			<key>Persistent ID</key><string>0FE4D22014F4EBDE</string>
			<key>Track Type</key><string>File</string>
			<key>Location</key><string>file://localhost/U:/Shared/Music/Crossfade%20-%20(2004)%20Crossfade%20-%20Colors.mp3</string>
			<key>File Folder Count</key><integer>-1</integer>
			<key>Library Folder Count</key><integer>-1</integer>
		</dict>
		<key>6846</key>
		<dict>
			<key>Track ID</key><integer>6846</integer>
			<key>Name</key><string>So Far Away</string>
			<key>Artist</key><string>Crossfade</string>
			<key>Album</key><string>Crossfade</string>
			<key>Genre</key><string>Other</string>
			<key>Kind</key><string>MPEG audio file</string>
			<key>Size</key><integer>5004120</integer>
			<key>Total Time</key><integer>206288</integer>
			<key>Year</key><integer>2004</integer>
			<key>Date Modified</key><date>2021-09-03T02:47:44Z</date>
			<key>Date Added</key><date>2025-05-22T23:58:47Z</date>
			<key>Bit Rate</key><integer>192</integer>
			<key>Sample Rate</key><integer>44100</integer>
			<key>Skip Count</key><integer>1</integer>
			<key>Skip Date</key><date>2020-07-07T21:28:39Z</date>
			<key>Normalization</key><integer>12168</integer>
			<key>Artwork Count</key><integer>1</integer>
			<key>Persistent ID</key><string>CDCF576F782C1893</string>
			<key>Track Type</key><string>File</string>
			<key>Location</key><string>file://localhost/U:/Shared/Music/Crossfade%20-%20(2004)%20Crossfade%20-%20So%20Far%20Away.mp3</string>
			<key>File Folder Count</key><integer>-1</integer>
			<key>Library Folder Count</key><integer>-1</integer>
		</dict>
		<key>6850</key>
		<dict>
			<key>Track ID</key><integer>6850</integer>
			<key>Name</key><string>The Deep End</string>
			<key>Artist</key><string>Crossfade</string>
			<key>Album</key><string>Crossfade</string>
			<key>Genre</key><string>Other</string>
			<key>Kind</key><string>MPEG audio file</string>
			<key>Size</key><integer>4941427</integer>
			<key>Total Time</key><integer>203676</integer>
			<key>Year</key><integer>2004</integer>
			<key>Date Modified</key><date>2021-09-03T02:47:51Z</date>
			<key>Date Added</key><date>2025-05-22T23:58:47Z</date>
			<key>Bit Rate</key><integer>192</integer>
			<key>Sample Rate</key><integer>44100</integer>
			<key>Normalization</key><integer>9087</integer>
			<key>Artwork Count</key><integer>1</integer>
			<key>Sort Name</key><string>Deep End</string>
			<key>Persistent ID</key><string>16C60F99B7C11899</string>
			<key>Track Type</key><string>File</string>
			<key>Location</key><string>file://localhost/U:/Shared/Music/Crossfade%20-%20(2004)%20Crossfade%20-%20The%20Deep%20End.mp3</string>
			<key>File Folder Count</key><integer>-1</integer>
			<key>Library Folder Count</key><integer>-1</integer>
		</dict>
		<key>6852</key>
		<dict>
			<key>Track ID</key><integer>6852</integer>
			<key>Name</key><string>The Unknown</string>
			<key>Artist</key><string>Crossfade</string>
			<key>Album</key><string>Crossfade</string>
			<key>Genre</key><string>AlternRock</string>
			<key>Kind</key><string>MPEG audio file</string>
			<key>Size</key><integer>4353780</integer>
			<key>Total Time</key><integer>179200</integer>
			<key>Year</key><integer>2004</integer>
			<key>Date Modified</key><date>2021-09-03T02:47:51Z</date>
			<key>Date Added</key><date>2025-05-22T23:58:48Z</date>
			<key>Bit Rate</key><integer>192</integer>
			<key>Sample Rate</key><integer>44100</integer>
			<key>Normalization</key><integer>3185</integer>
			<key>Artwork Count</key><integer>1</integer>
			<key>Sort Name</key><string>Unknown</string>
			<key>Persistent ID</key><string>1F5BCC173E648220</string>
			<key>Track Type</key><string>File</string>
			<key>Location</key><string>file://localhost/U:/Shared/Music/Crossfade%20-%20(2004)%20Crossfade%20-%20The%20Unknown.mp3</string>
			<key>File Folder Count</key><integer>-1</integer>
			<key>Library Folder Count</key><integer>-1</integer>
		</dict>
		<key>7410</key>
		<dict>
			<key>Track ID</key><integer>7410</integer>
			<key>Name</key><string>Painkiller (Dj Shadow vs Depeche Mode)</string>
			<key>Artist</key><string>Depeche Mode</string>
			<key>Genre</key><string>Electronic</string>
			<key>Kind</key><string>MPEG audio file</string>
			<key>Size</key><integer>7884672</integer>
			<key>Total Time</key><integer>394161</integer>
			<key>Year</key><integer>2004</integer>
			<key>Date Modified</key><date>2021-09-03T14:01:20Z</date>
			<key>Date Added</key><date>2025-05-22T23:59:17Z</date>
			<key>Bit Rate</key><integer>160</integer>
			<key>Sample Rate</key><integer>44100</integer>
			<key>Normalization</key><integer>3886</integer>
			<key>Persistent ID</key><string>8657D78A53EBB5F7</string>
			<key>Track Type</key><string>File</string>
			<key>Location</key><string>file://localhost/U:/Shared/Music/Depeche%20Mode%20-%20Painkiller%20(Kill%20The%20Pain%20-%20DJ%20Shadow%201998).mp3</string>
			<key>File Folder Count</key><integer>-1</integer>
			<key>Library Folder Count</key><integer>-1</integer>
		</dict>
		<key>8654</key>
		<dict>
			<key>Track ID</key><integer>8654</integer>
			<key>Name</key><string>Back The Fuck Up</string>
			<key>Artist</key><string>Fear Factory</string>
			<key>Album Artist</key><string>Fear Factory</string>
			<key>Composer</key><string>Burton C. Bell/Christian Olde Wolbers/Dino Cazares/Louis Freese/Raymond Herrera</string>
			<key>Album</key><string>Digimortal</string>
			<key>Genre</key><string>Other</string>
			<key>Kind</key><string>MPEG audio file</string>
			<key>Size</key><integer>5040982</integer>
			<key>Total Time</key><integer>189100</integer>
			<key>Track Number</key><integer>8</integer>
			<key>Year</key><integer>2001</integer>
			<key>Date Modified</key><date>2024-07-04T16:22:43Z</date>
			<key>Date Added</key><date>2025-05-23T00:00:16Z</date>
			<key>Bit Rate</key><integer>192</integer>
			<key>Sample Rate</key><integer>44100</integer>
			<key>Volume Adjustment</key><integer>100</integer>
			<key>Comments</key><string>CNMC 2001</string>
			<key>Normalization</key><integer>7631</integer>
			<key>Artwork Count</key><integer>1</integer>
			<key>Persistent ID</key><string>F4B4A392C53F9D24</string>
			<key>Track Type</key><string>File</string>
			<key>Location</key><string>file://localhost/U:/Shared/Music/Fear%20Factory%20-%20(2001)%20Digimortal%20-%20Back%20The%20Fuck%20Up.mp3</string>
			<key>File Folder Count</key><integer>-1</integer>
			<key>Library Folder Count</key><integer>-1</integer>
		</dict>
		<key>9598</key>
		<dict>
			<key>Track ID</key><integer>9598</integer>
			<key>Name</key><string>Poison Girl</string>
			<key>Artist</key><string>H.I.M.</string>
			<key>Album</key><string>Razorblade Romance</string>
			<key>Genre</key><string>Gothic Rock</string>
			<key>Kind</key><string>MPEG audio file</string>
			<key>Size</key><integer>3693708</integer>
			<key>Total Time</key><integer>230713</integer>
			<key>Year</key><integer>2000</integer>
			<key>Date Modified</key><date>2021-09-03T15:21:09Z</date>
			<key>Date Added</key><date>2025-05-23T00:01:10Z</date>
			<key>Bit Rate</key><integer>128</integer>
			<key>Sample Rate</key><integer>44100</integer>
			<key>Normalization</key><integer>3878</integer>
			<key>Persistent ID</key><string>F6E39266E7F313EC</string>
			<key>Track Type</key><string>File</string>
			<key>Location</key><string>file://localhost/U:/Shared/Music/H.I.M.%20-%20Poison%20Girl.mp3</string>
			<key>File Folder Count</key><integer>-1</integer>
			<key>Library Folder Count</key><integer>-1</integer>
		</dict>
		<key>10082</key>
		<dict>
			<key>Track ID</key><integer>10082</integer>
			<key>Name</key><string>Black &#38; White</string>
			<key>Artist</key><string>In Flames</string>
			<key>Album</key><string>Reroute to Remain </string>
			<key>Genre</key><string>Melodic Death Metal</string>
			<key>Kind</key><string>MPEG audio file</string>
			<key>Size</key><integer>5165252</integer>
			<key>Total Time</key><integer>213315</integer>
			<key>Year</key><integer>2002</integer>
			<key>Date Modified</key><date>2025-05-24T17:50:45Z</date>
			<key>Date Added</key><date>2025-05-23T00:01:34Z</date>
			<key>Bit Rate</key><integer>192</integer>
			<key>Sample Rate</key><integer>44100</integer>
			<key>Volume Adjustment</key><integer>100</integer>
			<key>Comments</key><string> </string>
			<key>Play Count</key><integer>4</integer>
			<key>Play Date</key><integer>3778921351</integer>
			<key>Play Date UTC</key><date>2023-09-30T15:22:31Z</date>
			<key>Skip Count</key><integer>1</integer>
			<key>Skip Date</key><date>2020-06-26T08:32:38Z</date>
			<key>Normalization</key><integer>8604</integer>
			<key>Artwork Count</key><integer>1</integer>
			<key>Persistent ID</key><string>887320A7EBD86DF7</string>
			<key>Track Type</key><string>File</string>
			<key>Location</key><string>file://localhost/U:/Shared/Music/In%20Flames%20-%20(2002)%20Reroute%20to%20Remain%20-%20Black%20and%20White.mp3</string>
			<key>File Folder Count</key><integer>-1</integer>
			<key>Library Folder Count</key><integer>-1</integer>
		</dict>
		<key>10084</key>
		<dict>
			<key>Track ID</key><integer>10084</integer>
			<key>Name</key><string>Cloud Connected</string>
			<key>Artist</key><string>In Flames</string>
			<key>Album</key><string>Reroute to Remain </string>
			<key>Genre</key><string>Melodic Death Metal</string>
			<key>Kind</key><string>MPEG audio file</string>
			<key>Size</key><integer>5341304</integer>
			<key>Total Time</key><integer>220342</integer>
			<key>Year</key><integer>2002</integer>
			<key>Date Modified</key><date>2025-05-24T17:50:45Z</date>
			<key>Date Added</key><date>2025-05-23T00:01:34Z</date>
			<key>Bit Rate</key><integer>192</integer>
			<key>Sample Rate</key><integer>44100</integer>
			<key>Volume Adjustment</key><integer>100</integer>
			<key>Comments</key><string> </string>
			<key>Play Count</key><integer>4</integer>
			<key>Play Date</key><integer>3778917446</integer>
			<key>Play Date UTC</key><date>2023-09-30T14:17:26Z</date>
			<key>Normalization</key><integer>9331</integer>
			<key>Artwork Count</key><integer>1</integer>
			<key>Persistent ID</key><string>748411FAEE82FD22</string>
			<key>Track Type</key><string>File</string>
			<key>Location</key><string>file://localhost/U:/Shared/Music/In%20Flames%20-%20(2002)%20Reroute%20to%20Remain%20-%20Cloud%20Connected.mp3</string>
			<key>File Folder Count</key><integer>-1</integer>
			<key>Library Folder Count</key><integer>-1</integer>
		</dict>
		<key>10096</key>
		<dict>
			<key>Track ID</key><integer>10096</integer>
			<key>Name</key><string>Free Fall</string>
			<key>Artist</key><string>In Flames</string>
			<key>Album</key><string>Reroute to Remain </string>
			<key>Genre</key><string>Melodic Death Metal</string>
			<key>Kind</key><string>MPEG audio file</string>
			<key>Size</key><integer>5763064</integer>
			<key>Total Time</key><integer>238262</integer>
			<key>Year</key><integer>2002</integer>
			<key>Date Modified</key><date>2025-05-24T17:50:46Z</date>
			<key>Date Added</key><date>2025-05-23T00:01:35Z</date>
			<key>Bit Rate</key><integer>192</integer>
			<key>Sample Rate</key><integer>44100</integer>
			<key>Volume Adjustment</key><integer>100</integer>
			<key>Comments</key><string> </string>
			<key>Play Count</key><integer>1</integer>
			<key>Play Date</key><integer>3746716272</integer>
			<key>Play Date UTC</key><date>2022-09-22T21:31:12Z</date>
			<key>Normalization</key><integer>8965</integer>
			<key>Artwork Count</key><integer>1</integer>
			<key>Persistent ID</key><string>18A5DAB59329397F</string>
			<key>Track Type</key><string>File</string>
			<key>Location</key><string>file://localhost/U:/Shared/Music/In%20Flames%20-%20(2002)%20Reroute%20to%20Remain%20-%20Free%20Fall.mp3</string>
			<key>File Folder Count</key><integer>-1</integer>
			<key>Library Folder Count</key><integer>-1</integer>
		</dict>
		<key>10100</key>
		<dict>
			<key>Track ID</key><integer>10100</integer>
			<key>Name</key><string>Minus</string>
			<key>Artist</key><string>In Flames</string>
			<key>Album</key><string>Reroute to Remain </string>
			<key>Genre</key><string>Melodic Death Metal</string>
			<key>Kind</key><string>MPEG audio file</string>
			<key>Size</key><integer>5459472</integer>
			<key>Total Time</key><integer>225593</integer>
			<key>Year</key><integer>2002</integer>
			<key>Date Modified</key><date>2025-05-24T17:50:46Z</date>
			<key>Date Added</key><date>2025-05-23T00:01:35Z</date>
			<key>Bit Rate</key><integer>192</integer>
			<key>Sample Rate</key><integer>44100</integer>
			<key>Volume Adjustment</key><integer>100</integer>
			<key>Comments</key><string> </string>
			<key>Play Count</key><integer>4</integer>
			<key>Play Date</key><integer>3778917667</integer>
			<key>Play Date UTC</key><date>2023-09-30T14:21:07Z</date>
			<key>Normalization</key><integer>9363</integer>
			<key>Artwork Count</key><integer>1</integer>
			<key>Persistent ID</key><string>F5B3840891228864</string>
			<key>Track Type</key><string>File</string>
			<key>Location</key><string>file://localhost/U:/Shared/Music/In%20Flames%20-%20(2002)%20Reroute%20to%20Remain%20-%20Minus.mp3</string>
			<key>File Folder Count</key><integer>-1</integer>
			<key>Library Folder Count</key><integer>-1</integer>
		</dict>
		<key>10108</key>
		<dict>
			<key>Track ID</key><integer>10108</integer>
			<key>Name</key><string>Trigger</string>
			<key>Artist</key><string>In Flames</string>
			<key>Album</key><string>Reroute to Remain </string>
			<key>Genre</key><string>Melodic Death Metal</string>
			<key>Kind</key><string>MPEG audio file</string>
			<key>Size</key><integer>7210390</integer>
			<key>Total Time</key><integer>298657</integer>
			<key>Year</key><integer>2002</integer>
			<key>Date Modified</key><date>2025-05-24T17:50:47Z</date>
			<key>Date Added</key><date>2025-05-23T00:01:36Z</date>
			<key>Bit Rate</key><integer>192</integer>
			<key>Sample Rate</key><integer>44100</integer>
			<key>Volume Adjustment</key><integer>100</integer>
			<key>Comments</key><string> </string>
			<key>Play Count</key><integer>4</integer>
			<key>Play Date</key><integer>3778917961</integer>
			<key>Play Date UTC</key><date>2023-09-30T14:26:01Z</date>
			<key>Normalization</key><integer>8450</integer>
			<key>Artwork Count</key><integer>1</integer>
			<key>Persistent ID</key><string>883F551CE59376B0</string>
			<key>Track Type</key><string>File</string>
			<key>Location</key><string>file://localhost/U:/Shared/Music/In%20Flames%20-%20(2002)%20Reroute%20to%20Remain%20-%20Trigger.mp3</string>
			<key>File Folder Count</key><integer>-1</integer>
			<key>Library Folder Count</key><integer>-1</integer>
		</dict>
		<key>10302</key>
		<dict>
			<key>Track ID</key><integer>10302</integer>
			<key>Name</key><string>Take You On A Cruise</string>
			<key>Artist</key><string>Interpol</string>
			<key>Album Artist</key><string>Interpol</string>
			<key>Composer</key><string>Interpol</string>
			<key>Album</key><string>Antics</string>
			<key>Genre</key><string>Rock</string>
			<key>Kind</key><string>MPEG audio file</string>
			<key>Size</key><integer>7079488</integer>
			<key>Total Time</key><integer>294452</integer>
			<key>Track Number</key><integer>4</integer>
			<key>Year</key><integer>2004</integer>
			<key>Date Modified</key><date>2021-09-03T15:38:40Z</date>
			<key>Date Added</key><date>2025-05-23T00:01:45Z</date>
			<key>Bit Rate</key><integer>192</integer>
			<key>Sample Rate</key><integer>44100</integer>
			<key>Normalization</key><integer>7092</integer>
			<key>Persistent ID</key><string>9B92628497EE241B</string>
			<key>Track Type</key><string>File</string>
			<key>Location</key><string>file://localhost/U:/Shared/Music/Interpol%20-%20(0000)%20Antics%20-%20Take%20you%20on%20a%20cruise.mp3</string>
			<key>File Folder Count</key><integer>-1</integer>
			<key>Library Folder Count</key><integer>-1</integer>
		</dict>
		<key>10314</key>
		<dict>
			<key>Track ID</key><integer>10314</integer>
			<key>Name</key><string>PDA</string>
			<key>Artist</key><string>Interpol</string>
			<key>Album Artist</key><string>Interpol</string>
			<key>Album</key><string>Precipitate EP</string>
			<key>Genre</key><string>Rock</string>
			<key>Kind</key><string>MPEG audio file</string>
			<key>Size</key><integer>13406208</integer>
			<key>Total Time</key><integer>335124</integer>
			<key>Track Number</key><integer>3</integer>
			<key>Year</key><integer>2001</integer>
			<key>Date Modified</key><date>2021-09-03T15:39:14Z</date>
			<key>Date Added</key><date>2025-05-23T00:01:46Z</date>
			<key>Bit Rate</key><integer>320</integer>
			<key>Sample Rate</key><integer>44100</integer>
			<key>Normalization</key><integer>6328</integer>
			<key>Persistent ID</key><string>BA166700DE3A57B6</string>
			<key>Track Type</key><string>File</string>
			<key>Location</key><string>file://localhost/U:/Shared/Music/Interpol%20-%20(0000)%20Precipitate%20EP%20-%20PDA.mp3</string>
			<key>File Folder Count</key><integer>-1</integer>
			<key>Library Folder Count</key><integer>-1</integer>
		</dict>
		<key>10344</key>
		<dict>
			<key>Track ID</key><integer>10344</integer>
			<key>Name</key><string>Roland</string>
			<key>Artist</key><string>Interpol</string>
			<key>Album</key><string>Turn On The Bright Lights</string>
			<key>Genre</key><string>Other</string>
			<key>Kind</key><string>MPEG audio file</string>
			<key>Size</key><integer>5184763</integer>
			<key>Total Time</key><integer>215588</integer>
			<key>Year</key><integer>2002</integer>
			<key>Date Modified</key><date>2021-09-03T15:40:02Z</date>
			<key>Date Added</key><date>2025-05-23T00:01:47Z</date>
			<key>Bit Rate</key><integer>192</integer>
			<key>Sample Rate</key><integer>44100</integer>
			<key>Normalization</key><integer>7543</integer>
			<key>Persistent ID</key><string>C59DD796C35EA0E9</string>
			<key>Track Type</key><string>File</string>
			<key>Location</key><string>file://localhost/U:/Shared/Music/Interpol%20-%20(2002)%20Turn%20on%20The%20Bright%20Lights%20-%20Roland.mp3</string>
			<key>File Folder Count</key><integer>-1</integer>
			<key>Library Folder Count</key><integer>-1</integer>
		</dict>
		<key>10352</key>
		<dict>
			<key>Track ID</key><integer>10352</integer>
			<key>Name</key><string>Untitled</string>
			<key>Artist</key><string>Interpol</string>
			<key>Album</key><string>Turn On The Bright Lights</string>
			<key>Genre</key><string>Other</string>
			<key>Kind</key><string>MPEG audio file</string>
			<key>Size</key><integer>5690705</integer>
			<key>Total Time</key><integer>236669</integer>
			<key>Year</key><integer>2002</integer>
			<key>Date Modified</key><date>2021-09-03T15:40:20Z</date>
			<key>Date Added</key><date>2025-05-23T00:01:48Z</date>
			<key>Bit Rate</key><integer>192</integer>
			<key>Sample Rate</key><integer>44100</integer>
			<key>Normalization</key><integer>5641</integer>
			<key>Persistent ID</key><string>2CDE88A5294048E9</string>
			<key>Track Type</key><string>File</string>
			<key>Location</key><string>file://localhost/U:/Shared/Music/Interpol%20-%20(2002)%20Turn%20on%20The%20Bright%20Lights%20-%20Untitled.mp3</string>
			<key>File Folder Count</key><integer>-1</integer>
			<key>Library Folder Count</key><integer>-1</integer>
		</dict>
		<key>11008</key>
		<dict>
			<key>Track ID</key><integer>11008</integer>
			<key>Name</key><string>Love Hangover</string>
			<key>Artist</key><string>Jettricks</string>
			<key>Album</key><string>Remote Control</string>
			<key>Genre</key><string>Lounge</string>
			<key>Kind</key><string>MPEG audio file</string>
			<key>Size</key><integer>13854233</integer>
			<key>Total Time</key><integer>346096</integer>
			<key>Year</key><integer>2008</integer>
			<key>Date Modified</key><date>2024-07-12T23:22:06Z</date>
			<key>Date Added</key><date>2025-05-23T00:02:27Z</date>
			<key>Bit Rate</key><integer>320</integer>
			<key>Sample Rate</key><integer>44100</integer>
			<key>Volume Adjustment</key><integer>96</integer>
			<key>Play Count</key><integer>27</integer>
			<key>Play Date</key><integer>3783259431</integer>
			<key>Play Date UTC</key><date>2023-11-19T19:23:51Z</date>
			<key>Skip Count</key><integer>2</integer>
			<key>Skip Date</key><date>2020-07-27T19:50:58Z</date>
			<key>Normalization</key><integer>1341</integer>
			<key>Persistent ID</key><string>8B14D29262475351</string>
			<key>Track Type</key><string>File</string>
			<key>Location</key><string>file://localhost/U:/Shared/Music/Jet%20Tricks%20-%20Love%20Hangover.mp3</string>
			<key>File Folder Count</key><integer>-1</integer>
			<key>Library Folder Count</key><integer>-1</integer>
		</dict>
		<key>11822</key>
		<dict>
			<key>Track ID</key><integer>11822</integer>
			<key>Name</key><string>Swamped</string>
			<key>Artist</key><string>Lacuna Coil</string>
			<key>Album</key><string>Comalies</string>
			<key>Genre</key><string>New Metal</string>
			<key>Kind</key><string>MPEG audio file</string>
			<key>Size</key><integer>5990441</integer>
			<key>Total Time</key><integer>240457</integer>
			<key>Track Number</key><integer>1</integer>
			<key>Year</key><integer>2002</integer>
			<key>Date Modified</key><date>2021-09-03T16:24:28Z</date>
			<key>Date Added</key><date>2025-05-23T00:03:07Z</date>
			<key>Bit Rate</key><integer>192</integer>
			<key>Sample Rate</key><integer>44100</integer>
			<key>Play Count</key><integer>5</integer>
			<key>Play Date</key><integer>3773045975</integer>
			<key>Play Date UTC</key><date>2023-07-24T15:19:35Z</date>
			<key>Skip Count</key><integer>1</integer>
			<key>Skip Date</key><date>2022-09-08T22:09:58Z</date>
			<key>Normalization</key><integer>9301</integer>
			<key>Artwork Count</key><integer>1</integer>
			<key>Persistent ID</key><string>10F5E84F6BA63B13</string>
			<key>Track Type</key><string>File</string>
			<key>Location</key><string>file://localhost/U:/Shared/Music/Lacuna%20Coil%20-%20(2002)%20Comalies%20-%20Swamped.mp3</string>
			<key>File Folder Count</key><integer>-1</integer>
			<key>Library Folder Count</key><integer>-1</integer>
		</dict>
		<key>12828</key>
		<dict>
			<key>Track ID</key><integer>12828</integer>
			<key>Name</key><string>Get Together</string>
			<key>Artist</key><string>Madonna</string>
			<key>Album</key><string>Confessions On A Dance Floor</string>
			<key>Kind</key><string>MPEG audio file</string>
			<key>Size</key><integer>7935950</integer>
			<key>Total Time</key><integer>328933</integer>
			<key>Year</key><integer>2005</integer>
			<key>Date Modified</key><date>2024-02-26T14:11:00Z</date>
			<key>Date Added</key><date>2025-05-23T00:03:57Z</date>
			<key>Bit Rate</key><integer>192</integer>
			<key>Sample Rate</key><integer>44100</integer>
			<key>Volume Adjustment</key><integer>102</integer>
			<key>Play Count</key><integer>9</integer>
			<key>Play Date</key><integer>3739434972</integer>
			<key>Play Date UTC</key><date>2022-06-30T14:56:12Z</date>
			<key>Normalization</key><integer>3865</integer>
			<key>Artwork Count</key><integer>1</integer>
			<key>Persistent ID</key><string>B9DE81D8F58B733B</string>
			<key>Track Type</key><string>File</string>
			<key>Location</key><string>file://localhost/U:/Shared/Music/Madonna%20-%20(2005)%20Confessions%20On%20A%20Dancefloor%20-%20Get%20Together.mp3</string>
			<key>File Folder Count</key><integer>-1</integer>
			<key>Library Folder Count</key><integer>-1</integer>
		</dict>
		<key>13594</key>
		<dict>
			<key>Track ID</key><integer>13594</integer>
			<key>Name</key><string>Blood stained</string>
			<key>Artist</key><string>Mnemic</string>
			<key>Album</key><string>Mechanical Spin Phenomena</string>
			<key>Kind</key><string>MPEG audio file</string>
			<key>Size</key><integer>9187962</integer>
			<key>Total Time</key><integer>380551</integer>
			<key>Track Number</key><integer>2</integer>
			<key>Year</key><integer>2003</integer>
			<key>Date Modified</key><date>2021-09-03T17:46:37Z</date>
			<key>Date Added</key><date>2025-05-23T00:04:36Z</date>
			<key>Bit Rate</key><integer>192</integer>
			<key>Sample Rate</key><integer>44100</integer>
			<key>Comments</key><string>fff</string>
			<key>Normalization</key><integer>11314</integer>
			<key>Artwork Count</key><integer>1</integer>
			<key>Persistent ID</key><string>4666276D1A4772C7</string>
			<key>Track Type</key><string>File</string>
			<key>Location</key><string>file://localhost/U:/Shared/Music/Mnemic%20-%20(2003)%20Mechanical%20Spin%20Phemomena%20-%20Blood%20Stained.mp3</string>
			<key>File Folder Count</key><integer>-1</integer>
			<key>Library Folder Count</key><integer>-1</integer>
		</dict>
		<key>13600</key>
		<dict>
			<key>Track ID</key><integer>13600</integer>
			<key>Name</key><string>Liquid</string>
			<key>Artist</key><string>Mnemic</string>
			<key>Album</key><string>Mechanical Spin Phenomena</string>
			<key>Genre</key><string>Metal</string>
			<key>Kind</key><string>MPEG audio file</string>
			<key>Size</key><integer>6835280</integer>
			<key>Total Time</key><integer>282383</integer>
			<key>Year</key><integer>2003</integer>
			<key>Date Modified</key><date>2021-09-03T17:46:49Z</date>
			<key>Date Added</key><date>2025-05-23T00:04:36Z</date>
			<key>Bit Rate</key><integer>192</integer>
			<key>Sample Rate</key><integer>44100</integer>
			<key>Comments</key><string>FFF</string>
			<key>Normalization</key><integer>11251</integer>
			<key>Artwork Count</key><integer>1</integer>
			<key>Persistent ID</key><string>6753C50E3FB667B9</string>
			<key>Track Type</key><string>File</string>
			<key>Location</key><string>file://localhost/U:/Shared/Music/Mnemic%20-%20(2003)%20Mechanical%20Spin%20Phemomena%20-%20Liquid.mp3</string>
			<key>File Folder Count</key><integer>-1</integer>
			<key>Library Folder Count</key><integer>-1</integer>
		</dict>
		<key>13610</key>
		<dict>
			<key>Track ID</key><integer>13610</integer>
			<key>Name</key><string>Deathbox</string>
			<key>Artist</key><string>Mnemic</string>
			<key>Album</key><string>The Audio Injected Soul</string>
			<key>Genre</key><string>Metal</string>
			<key>Kind</key><string>MPEG audio file</string>
			<key>Size</key><integer>8191316</integer>
			<key>Total Time</key><integer>272457</integer>
			<key>Track Number</key><integer>4</integer>
			<key>Year</key><integer>2004</integer>
			<key>Date Modified</key><date>2021-09-03T17:47:09Z</date>
			<key>Date Added</key><date>2025-05-23T00:04:37Z</date>
			<key>Bit Rate</key><integer>239</integer>
			<key>Sample Rate</key><integer>44100</integer>
			<key>Normalization</key><integer>12876</integer>
			<key>Artwork Count</key><integer>1</integer>
			<key>Sort Album</key><string>Audio Injected Soul</string>
			<key>Persistent ID</key><string>DA1F0521F952942D</string>
			<key>Track Type</key><string>File</string>
			<key>Location</key><string>file://localhost/U:/Shared/Music/Mnemic%20-%20(2004)%20The%20Audio%20Injected%20Soul%20-%20Deathbox.mp3</string>
			<key>File Folder Count</key><integer>-1</integer>
			<key>Library Folder Count</key><integer>-1</integer>
		</dict>
		<key>13612</key>
		<dict>
			<key>Track ID</key><integer>13612</integer>
			<key>Name</key><string>Door 2.12</string>
			<key>Artist</key><string>Mnemic</string>
			<key>Album</key><string>The Audio Injected Soul</string>
			<key>Genre</key><string>Metal</string>
			<key>Kind</key><string>MPEG audio file</string>
			<key>Size</key><integer>8589879</integer>
			<key>Total Time</key><integer>262608</integer>
			<key>Track Number</key><integer>2</integer>
			<key>Year</key><integer>2004</integer>
			<key>Date Modified</key><date>2021-09-03T17:47:18Z</date>
			<key>Date Added</key><date>2025-05-23T00:04:37Z</date>
			<key>Bit Rate</key><integer>260</integer>
			<key>Sample Rate</key><integer>44100</integer>
			<key>Skip Count</key><integer>1</integer>
			<key>Skip Date</key><date>2024-01-29T20:51:52Z</date>
			<key>Normalization</key><integer>15323</integer>
			<key>Artwork Count</key><integer>1</integer>
			<key>Sort Album</key><string>Audio Injected Soul</string>
			<key>Persistent ID</key><string>BE774DD1A55DDA1E</string>
			<key>Track Type</key><string>File</string>
			<key>Location</key><string>file://localhost/U:/Shared/Music/Mnemic%20-%20(2004)%20The%20Audio%20Injected%20Soul%20-%20Door%202.12.mp3</string>
			<key>File Folder Count</key><integer>-1</integer>
			<key>Library Folder Count</key><integer>-1</integer>
		</dict>
		<key>13616</key>
		<dict>
			<key>Track ID</key><integer>13616</integer>
			<key>Name</key><string>Illuminate</string>
			<key>Artist</key><string>Mnemic</string>
			<key>Album</key><string>The Audio Injected Soul</string>
			<key>Genre</key><string>Metal</string>
			<key>Kind</key><string>MPEG audio file</string>
			<key>Size</key><integer>9206663</integer>
			<key>Total Time</key><integer>303360</integer>
			<key>Track Number</key><integer>3</integer>
			<key>Year</key><integer>2004</integer>
			<key>Date Modified</key><date>2021-09-03T17:47:25Z</date>
			<key>Date Added</key><date>2025-05-23T00:04:37Z</date>
			<key>Bit Rate</key><integer>241</integer>
			<key>Sample Rate</key><integer>44100</integer>
			<key>Normalization</key><integer>14764</integer>
			<key>Artwork Count</key><integer>1</integer>
			<key>Sort Album</key><string>Audio Injected Soul</string>
			<key>Persistent ID</key><string>7B013CCF7DD2DBC4</string>
			<key>Track Type</key><string>File</string>
			<key>Location</key><string>file://localhost/U:/Shared/Music/Mnemic%20-%20(2004)%20The%20Audio%20Injected%20Soul%20-%20Illuminate.mp3</string>
			<key>File Folder Count</key><integer>-1</integer>
			<key>Library Folder Count</key><integer>-1</integer>
		</dict>
		<key>13620</key>
		<dict>
			<key>Track ID</key><integer>13620</integer>
			<key>Name</key><string>Mindsaver</string>
			<key>Artist</key><string>Mnemic</string>
			<key>Album</key><string>The Audio Injected Soul</string>
			<key>Genre</key><string>Metal</string>
			<key>Kind</key><string>MPEG audio file</string>
			<key>Size</key><integer>7605197</integer>
			<key>Total Time</key><integer>252760</integer>
			<key>Track Number</key><integer>7</integer>
			<key>Year</key><integer>2004</integer>
			<key>Date Modified</key><date>2021-09-03T17:47:28Z</date>
			<key>Date Added</key><date>2025-05-23T00:04:38Z</date>
			<key>Bit Rate</key><integer>239</integer>
			<key>Sample Rate</key><integer>44100</integer>
			<key>Normalization</key><integer>12937</integer>
			<key>Artwork Count</key><integer>1</integer>
			<key>Sort Album</key><string>Audio Injected Soul</string>
			<key>Persistent ID</key><string>8E777916D416F466</string>
			<key>Track Type</key><string>File</string>
			<key>Location</key><string>file://localhost/U:/Shared/Music/Mnemic%20-%20(2004)%20The%20Audio%20Injected%20Soul%20-%20Mindsaver.mp3</string>
			<key>File Folder Count</key><integer>-1</integer>
			<key>Library Folder Count</key><integer>-1</integer>
		</dict>
		<key>13622</key>
		<dict>
			<key>Track ID</key><integer>13622</integer>
			<key>Name</key><string>Overdose In The Hall Of Fame</string>
			<key>Artist</key><string>Mnemic</string>
			<key>Album</key><string>The Audio Injected Soul</string>
			<key>Genre</key><string>Metal</string>
			<key>Kind</key><string>MPEG audio file</string>
			<key>Size</key><integer>9663614</integer>
			<key>Total Time</key><integer>315924</integer>
			<key>Track Number</key><integer>8</integer>
			<key>Year</key><integer>2004</integer>
			<key>Date Modified</key><date>2021-09-03T17:47:34Z</date>
			<key>Date Added</key><date>2025-05-23T00:04:38Z</date>
			<key>Bit Rate</key><integer>243</integer>
			<key>Sample Rate</key><integer>44100</integer>
			<key>Normalization</key><integer>9506</integer>
			<key>Artwork Count</key><integer>1</integer>
			<key>Sort Album</key><string>Audio Injected Soul</string>
			<key>Persistent ID</key><string>200963DD28E4BEDE</string>
			<key>Track Type</key><string>File</string>
			<key>Location</key><string>file://localhost/U:/Shared/Music/Mnemic%20-%20(2004)%20The%20Audio%20Injected%20Soul%20-%20Overdose%20in%20the%20Hall%20of%20Fame.mp3</string>
			<key>File Folder Count</key><integer>-1</integer>
			<key>Library Folder Count</key><integer>-1</integer>
		</dict>
		<key>15944</key>
		<dict>
			<key>Track ID</key><integer>15944</integer>
			<key>Name</key><string>Fate In Motion</string>
			<key>Artist</key><string>Soilwork</string>
			<key>Album</key><string>Stabbing The Drama</string>
			<key>Genre</key><string>Death Metal</string>
			<key>Kind</key><string>MPEG audio file</string>
			<key>Size</key><integer>6265627</integer>
			<key>Total Time</key><integer>201325</integer>
			<key>Track Number</key><integer>9</integer>
			<key>Year</key><integer>2005</integer>
			<key>Date Modified</key><date>2023-10-18T11:58:14Z</date>
			<key>Date Added</key><date>2025-05-23T00:06:51Z</date>
			<key>Bit Rate</key><integer>246</integer>
			<key>Sample Rate</key><integer>44100</integer>
			<key>Volume Adjustment</key><integer>100</integer>
			<key>Comments</key><string>Dirty Jer-Z</string>
			<key>Play Count</key><integer>2</integer>
			<key>Play Date</key><integer>3746002938</integer>
			<key>Play Date UTC</key><date>2022-09-14T15:22:18Z</date>
			<key>Skip Count</key><integer>1</integer>
			<key>Skip Date</key><date>2023-05-16T19:36:47Z</date>
			<key>Normalization</key><integer>11607</integer>
			<key>Artwork Count</key><integer>1</integer>
			<key>Persistent ID</key><string>2C470235F579B309</string>
			<key>Track Type</key><string>File</string>
			<key>Location</key><string>file://localhost/U:/Shared/Music/Soilwork%20-%20(2005)%20Stabbing%20The%20Drama%20-%20Fate%20In%20Motion.mp3</string>
			<key>File Folder Count</key><integer>-1</integer>
			<key>Library Folder Count</key><integer>-1</integer>
		</dict>
		<key>15946</key>
		<dict>
			<key>Track ID</key><integer>15946</integer>
			<key>Name</key><string>Nerve</string>
			<key>Artist</key><string>Soilwork</string>
			<key>Album</key><string>Stabbing The Drama</string>
			<key>Genre</key><string>Death Metal</string>
			<key>Kind</key><string>MPEG audio file</string>
			<key>Size</key><integer>6766348</integer>
			<key>Total Time</key><integer>218801</integer>
			<key>Track Number</key><integer>5</integer>
			<key>Year</key><integer>2005</integer>
			<key>Date Modified</key><date>2023-10-18T11:58:11Z</date>
			<key>Date Added</key><date>2025-05-23T00:06:51Z</date>
			<key>Bit Rate</key><integer>244</integer>
			<key>Sample Rate</key><integer>44100</integer>
			<key>Volume Adjustment</key><integer>100</integer>
			<key>Comments</key><string>Dirty Jer-Z</string>
			<key>Normalization</key><integer>10232</integer>
			<key>Artwork Count</key><integer>1</integer>
			<key>Persistent ID</key><string>019295567383B805</string>
			<key>Track Type</key><string>File</string>
			<key>Location</key><string>file://localhost/U:/Shared/Music/Soilwork%20-%20(2005)%20Stabbing%20The%20Drama%20-%20Nerve.mp3</string>
			<key>File Folder Count</key><integer>-1</integer>
			<key>Library Folder Count</key><integer>-1</integer>
		</dict>
		<key>15948</key>
		<dict>
			<key>Track ID</key><integer>15948</integer>
			<key>Name</key><string>Observation Slave</string>
			<key>Artist</key><string>Soilwork</string>
			<key>Album</key><string>Stabbing The Drama</string>
			<key>Genre</key><string>Death Metal</string>
			<key>Kind</key><string>MPEG audio file</string>
			<key>Size</key><integer>7841382</integer>
			<key>Total Time</key><integer>249573</integer>
			<key>Track Number</key><integer>8</integer>
			<key>Year</key><integer>2005</integer>
			<key>Date Modified</key><date>2023-10-18T11:58:11Z</date>
			<key>Date Added</key><date>2025-05-23T00:06:51Z</date>
			<key>Bit Rate</key><integer>249</integer>
			<key>Sample Rate</key><integer>44100</integer>
			<key>Volume Adjustment</key><integer>100</integer>
			<key>Comments</key><string>Dirty Jer-Z</string>
			<key>Skip Count</key><integer>1</integer>
			<key>Skip Date</key><date>2023-12-06T15:03:51Z</date>
			<key>Normalization</key><integer>12341</integer>
			<key>Artwork Count</key><integer>1</integer>
			<key>Persistent ID</key><string>F191CD6D74BE6794</string>
			<key>Track Type</key><string>File</string>
			<key>Location</key><string>file://localhost/U:/Shared/Music/Soilwork%20-%20(2005)%20Stabbing%20The%20Drama%20-%20Observation%20Slave.mp3</string>
			<key>File Folder Count</key><integer>-1</integer>
			<key>Library Folder Count</key><integer>-1</integer>
		</dict>
		<key>15952</key>
		<dict>
			<key>Track ID</key><integer>15952</integer>
			<key>Name</key><string>Stabbing The Drama</string>
			<key>Artist</key><string>Soilwork</string>
			<key>Album</key><string>Stabbing The Drama</string>
			<key>Genre</key><string>Death Metal</string>
			<key>Kind</key><string>MPEG audio file</string>
			<key>Size</key><integer>8407985</integer>
			<key>Total Time</key><integer>273893</integer>
			<key>Track Number</key><integer>1</integer>
			<key>Year</key><integer>2005</integer>
			<key>Date Modified</key><date>2023-10-18T11:58:08Z</date>
			<key>Date Added</key><date>2025-05-23T00:06:51Z</date>
			<key>Bit Rate</key><integer>243</integer>
			<key>Sample Rate</key><integer>44100</integer>
			<key>Volume Adjustment</key><integer>100</integer>
			<key>Comments</key><string>Dirty Jer-Z</string>
			<key>Skip Count</key><integer>1</integer>
			<key>Skip Date</key><date>2023-10-18T11:57:47Z</date>
			<key>Normalization</key><integer>12624</integer>
			<key>Artwork Count</key><integer>1</integer>
			<key>Persistent ID</key><string>9A4D95C487952CCA</string>
			<key>Track Type</key><string>File</string>
			<key>Location</key><string>file://localhost/U:/Shared/Music/Soilwork%20-%20(2005)%20Stabbing%20The%20Drama%20-%20Stabbing%20The%20Drama.mp3</string>
			<key>File Folder Count</key><integer>-1</integer>
			<key>Library Folder Count</key><integer>-1</integer>
		</dict>
		<key>15960</key>
		<dict>
			<key>Track ID</key><integer>15960</integer>
			<key>Name</key><string>If Possible</string>
			<key>Artist</key><string>Soilwork</string>
			<key>Album</key><string>Stabbing The Drama</string>
			<key>Genre</key><string>Death Metal</string>
			<key>Kind</key><string>MPEG audio file</string>
			<key>Size</key><integer>8297834</integer>
			<key>Total Time</key><integer>290115</integer>
			<key>Track Number</key><integer>11</integer>
			<key>Year</key><integer>2005</integer>
			<key>Date Modified</key><date>2023-10-18T11:58:13Z</date>
			<key>Date Added</key><date>2025-05-23T00:06:51Z</date>
			<key>Bit Rate</key><integer>226</integer>
			<key>Sample Rate</key><integer>44100</integer>
			<key>Volume Adjustment</key><integer>100</integer>
			<key>Comments</key><string>Dirty Jer-Z</string>
			<key>Normalization</key><integer>11641</integer>
			<key>Artwork Count</key><integer>1</integer>
			<key>Persistent ID</key><string>5C15ED24182F92BA</string>
			<key>Track Type</key><string>File</string>
			<key>Location</key><string>file://localhost/U:/Shared/Music/Soilwork%20-%20(2005)%20Stabbing%20The%20Drama%20-%20Wherever%20Thorns%20May%20Grow.mp3</string>
			<key>File Folder Count</key><integer>-1</integer>
			<key>Library Folder Count</key><integer>-1</integer>
		</dict>
		<key>16230</key>
		<dict>
			<key>Track ID</key><integer>16230</integer>
			<key>Name</key><string>Invincible</string>
			<key>Artist</key><string>Static-X</string>
			<key>Album Artist</key><string>Static-X</string>
			<key>Composer</key><string>Ken Jay/Tripp Eisen/Wayne Static</string>
			<key>Album</key><string>Shadow Zone</string>
			<key>Genre</key><string>Metal</string>
			<key>Kind</key><string>MPEG audio file</string>
			<key>Size</key><integer>5999780</integer>
			<key>Total Time</key><integer>244610</integer>
			<key>Track Number</key><integer>13</integer>
			<key>Year</key><integer>2003</integer>
			<key>Date Modified</key><date>2024-06-17T17:36:53Z</date>
			<key>Date Added</key><date>2025-05-23T00:07:07Z</date>
			<key>Bit Rate</key><integer>192</integer>
			<key>Sample Rate</key><integer>44100</integer>
			<key>Volume Adjustment</key><integer>100</integer>
			<key>Normalization</key><integer>6043</integer>
			<key>Artwork Count</key><integer>1</integer>
			<key>Persistent ID</key><string>BDEB36C0E63C0A56</string>
			<key>Track Type</key><string>File</string>
			<key>Location</key><string>file://localhost/U:/Shared/Music/Static-X%20-%20(2003)%20Shadow%20Zone%20-%20Invincible.mp3</string>
			<key>File Folder Count</key><integer>-1</integer>
			<key>Library Folder Count</key><integer>-1</integer>
		</dict>
		<key>16710</key>
		<dict>
			<key>Track ID</key><integer>16710</integer>
			<key>Name</key><string>Addicted</string>
			<key>Artist</key><string>The Blank Theory</string>
			<key>Album</key><string>Beyond The Calm Of The Corridor</string>
			<key>Genre</key><string>New Metal</string>
			<key>Kind</key><string>MPEG audio file</string>
			<key>Size</key><integer>3641063</integer>
			<key>Total Time</key><integer>226220</integer>
			<key>Track Number</key><integer>2</integer>
			<key>Year</key><integer>2002</integer>
			<key>Date Modified</key><date>2021-09-03T19:03:07Z</date>
			<key>Date Added</key><date>2025-05-23T00:07:31Z</date>
			<key>Bit Rate</key><integer>128</integer>
			<key>Sample Rate</key><integer>44100</integer>
			<key>Normalization</key><integer>7366</integer>
			<key>Artwork Count</key><integer>1</integer>
			<key>Sort Artist</key><string>Blank Theory</string>
			<key>Persistent ID</key><string>DA013292A0EC8C40</string>
			<key>Track Type</key><string>File</string>
			<key>Location</key><string>file://localhost/U:/Shared/Music/The%20Blank%20Theory%20-%20(2002)%20Beyond%20The%20Calm%20Of%20The%20Corridor%20-%20Addicted.mp3</string>
			<key>File Folder Count</key><integer>-1</integer>
			<key>Library Folder Count</key><integer>-1</integer>
		</dict>
		<key>16728</key>
		<dict>
			<key>Track ID</key><integer>16728</integer>
			<key>Name</key><string>Middle Of Nowhere</string>
			<key>Artist</key><string>The Blank Theory</string>
			<key>Album</key><string>Beyond The Calm Of The Corridor</string>
			<key>Genre</key><string>New Metal</string>
			<key>Kind</key><string>MPEG audio file</string>
			<key>Size</key><integer>3979286</integer>
			<key>Total Time</key><integer>247405</integer>
			<key>Track Number</key><integer>1</integer>
			<key>Year</key><integer>2002</integer>
			<key>Date Modified</key><date>2021-09-03T19:03:26Z</date>
			<key>Date Added</key><date>2025-05-23T00:07:32Z</date>
			<key>Bit Rate</key><integer>128</integer>
			<key>Sample Rate</key><integer>44100</integer>
			<key>Normalization</key><integer>12196</integer>
			<key>Artwork Count</key><integer>1</integer>
			<key>Sort Artist</key><string>Blank Theory</string>
			<key>Persistent ID</key><string>1C4A33AABE65EBE1</string>
			<key>Track Type</key><string>File</string>
			<key>Location</key><string>file://localhost/U:/Shared/Music/The%20Blank%20Theory%20-%20(2002)%20Beyond%20The%20Calm%20Of%20The%20Corridor%20-%20Middle%20Of%20Nowhere.mp3</string>
			<key>File Folder Count</key><integer>-1</integer>
			<key>Library Folder Count</key><integer>-1</integer>
		</dict>
		<key>17286</key>
		<dict>
			<key>Track ID</key><integer>17286</integer>
			<key>Name</key><string>Enjoy the Silence</string>
			<key>Artist</key><string>Depeche Mode</string>
			<key>Composer</key><string>Martin L. Gore</string>
			<key>Album</key><string>Essentials</string>
			<key>Genre</key><string>Pop</string>
			<key>Kind</key><string>MPEG audio file</string>
			<key>Size</key><integer>10277712</integer>
			<key>Total Time</key><integer>255164</integer>
			<key>Track Number</key><integer>1</integer>
			<key>BPM</key><integer>112</integer>
			<key>Date Modified</key><date>2021-09-03T13:59:18Z</date>
			<key>Date Added</key><date>2025-05-23T00:08:04Z</date>
			<key>Bit Rate</key><integer>320</integer>
			<key>Sample Rate</key><integer>44100</integer>
			<key>Comments</key><string>Freak37</string>
			<key>Play Count</key><integer>22</integer>
			<key>Play Date</key><integer>3778862991</integer>
			<key>Play Date UTC</key><date>2023-09-29T23:09:51Z</date>
			<key>Skip Count</key><integer>1</integer>
			<key>Skip Date</key><date>2020-06-21T03:42:03Z</date>
			<key>Normalization</key><integer>4961</integer>
			<key>Artwork Count</key><integer>1</integer>
			<key>Persistent ID</key><string>F4299C8C3F4B8392</string>
			<key>Track Type</key><string>File</string>
			<key>Location</key><string>file://localhost/U:/Shared/Music/Depeche%20Mode%20%E2%80%93%20(2018)%20Essentials%20-%20Enjoy%20the%20Silence.mp3</string>
			<key>File Folder Count</key><integer>-1</integer>
			<key>Library Folder Count</key><integer>-1</integer>
		</dict>
		<key>18582</key>
		<dict>
			<key>Track ID</key><integer>18582</integer>
			<key>Name</key><string>Un Simple Histoire (A Simple History)</string>
			<key>Artist</key><string>Thievery Corporation</string>
			<key>Album</key><string>The Richest Man in Babylon</string>
			<key>Kind</key><string>MPEG audio file</string>
			<key>Size</key><integer>9136345</integer>
			<key>Total Time</key><integer>225541</integer>
			<key>Track Count</key><integer>14</integer>
			<key>Year</key><integer>2002</integer>
			<key>Date Modified</key><date>2024-07-12T23:22:19Z</date>
			<key>Date Added</key><date>2025-05-23T00:09:09Z</date>
			<key>Bit Rate</key><integer>320</integer>
			<key>Sample Rate</key><integer>44100</integer>
			<key>Volume Adjustment</key><integer>96</integer>
			<key>Play Count</key><integer>3</integer>
			<key>Play Date</key><integer>3766104891</integer>
			<key>Play Date UTC</key><date>2023-05-05T07:14:51Z</date>
			<key>Normalization</key><integer>1259</integer>
			<key>Artwork Count</key><integer>1</integer>
			<key>Sort Album</key><string>Richest Man in Babylon</string>
			<key>Persistent ID</key><string>13AB205B8425A787</string>
			<key>Track Type</key><string>File</string>
			<key>Location</key><string>file://localhost/U:/Shared/Music/Thievery%20Corporation%20-%20(2002)%20The%20Richest%20Man%20in%20Babylon%20-%20Un%20Simple%20Histoire%20A%20Simple%20History.mp3</string>
			<key>File Folder Count</key><integer>-1</integer>
			<key>Library Folder Count</key><integer>-1</integer>
		</dict>
		<key>18604</key>
		<dict>
			<key>Track ID</key><integer>18604</integer>
			<key>Name</key><string>Heavens Gonna Burn Your Eyes</string>
			<key>Artist</key><string>Thievery Corporation</string>
			<key>Album</key><string>The Richest Man in Babylon</string>
			<key>Kind</key><string>MPEG audio file</string>
			<key>Size</key><integer>10133177</integer>
			<key>Total Time</key><integer>250462</integer>
			<key>Track Count</key><integer>14</integer>
			<key>Year</key><integer>2002</integer>
			<key>Date Modified</key><date>2024-07-12T23:22:14Z</date>
			<key>Date Added</key><date>2025-05-23T00:09:10Z</date>
			<key>Bit Rate</key><integer>320</integer>
			<key>Sample Rate</key><integer>44100</integer>
			<key>Volume Adjustment</key><integer>96</integer>
			<key>Play Count</key><integer>4</integer>
			<key>Play Date</key><integer>3766105137</integer>
			<key>Play Date UTC</key><date>2023-05-05T07:18:57Z</date>
			<key>Normalization</key><integer>1601</integer>
			<key>Artwork Count</key><integer>1</integer>
			<key>Sort Album</key><string>Richest Man in Babylon</string>
			<key>Persistent ID</key><string>BEBDD2CDBA60A310</string>
			<key>Track Type</key><string>File</string>
			<key>Location</key><string>file://localhost/U:/Shared/Music/Thievery%20Corporation%20-%20(2002)%20The%20Richest%20Man%20in%20Babylon%20-%20Heavens%20Gonna%20Burn%20Your%20Eyes.mp3</string>
			<key>File Folder Count</key><integer>-1</integer>
			<key>Library Folder Count</key><integer>-1</integer>
		</dict>
	</dict>
	<key>Playlists</key>
	<array>
		<dict>
			<key>Name</key><string>Back to 2005</string>
			<key>Description</key><string></string>
			<key>Playlist ID</key><integer>61408</integer>
			<key>Playlist Persistent ID</key><string>3B6DC4AD02F0E194</string>
			<key>All Items</key><true/>
			<key>Playlist Items</key>
			<array>
				<dict>
					<key>Track ID</key><integer>13594</integer>
				</dict>
				<dict>
					<key>Track ID</key><integer>13600</integer>
				</dict>
				<dict>
					<key>Track ID</key><integer>13612</integer>
				</dict>
				<dict>
					<key>Track ID</key><integer>13616</integer>
				</dict>
				<dict>
					<key>Track ID</key><integer>13610</integer>
				</dict>
				<dict>
					<key>Track ID</key><integer>13620</integer>
				</dict>
				<dict>
					<key>Track ID</key><integer>13622</integer>
				</dict>
				<dict>
					<key>Track ID</key><integer>6838</integer>
				</dict>
				<dict>
					<key>Track ID</key><integer>6840</integer>
				</dict>
				<dict>
					<key>Track ID</key><integer>6850</integer>
				</dict>
				<dict>
					<key>Track ID</key><integer>6846</integer>
				</dict>
				<dict>
					<key>Track ID</key><integer>10314</integer>
				</dict>
				<dict>
					<key>Track ID</key><integer>10302</integer>
				</dict>
				<dict>
					<key>Track ID</key><integer>7410</integer>
				</dict>
				<dict>
					<key>Track ID</key><integer>10344</integer>
				</dict>
				<dict>
					<key>Track ID</key><integer>10352</integer>
				</dict>
				<dict>
					<key>Track ID</key><integer>3046</integer>
				</dict>
				<dict>
					<key>Track ID</key><integer>8654</integer>
				</dict>
				<dict>
					<key>Track ID</key><integer>9598</integer>
				</dict>
				<dict>
					<key>Track ID</key><integer>11008</integer>
				</dict>
				<dict>
					<key>Track ID</key><integer>16710</integer>
				</dict>
				<dict>
					<key>Track ID</key><integer>16728</integer>
				</dict>
				<dict>
					<key>Track ID</key><integer>6258</integer>
				</dict>
				<dict>
					<key>Track ID</key><integer>6260</integer>
				</dict>
				<dict>
					<key>Track ID</key><integer>2790</integer>
				</dict>
				<dict>
					<key>Track ID</key><integer>11822</integer>
				</dict>
				<dict>
					<key>Track ID</key><integer>16230</integer>
				</dict>
				<dict>
					<key>Track ID</key><integer>10096</integer>
				</dict>
				<dict>
					<key>Track ID</key><integer>10082</integer>
				</dict>
				<dict>
					<key>Track ID</key><integer>10084</integer>
				</dict>
				<dict>
					<key>Track ID</key><integer>10100</integer>
				</dict>
				<dict>
					<key>Track ID</key><integer>10108</integer>
				</dict>
				<dict>
					<key>Track ID</key><integer>15952</integer>
				</dict>
				<dict>
					<key>Track ID</key><integer>15946</integer>
				</dict>
				<dict>
					<key>Track ID</key><integer>15948</integer>
				</dict>
				<dict>
					<key>Track ID</key><integer>15944</integer>
				</dict>
				<dict>
					<key>Track ID</key><integer>15960</integer>
				</dict>
				<dict>
					<key>Track ID</key><integer>17286</integer>
				</dict>
				<dict>
					<key>Track ID</key><integer>6852</integer>
				</dict>
				<dict>
					<key>Track ID</key><integer>12828</integer>
				</dict>
				<dict>
					<key>Track ID</key><integer>18604</integer>
				</dict>
				<dict>
					<key>Track ID</key><integer>18582</integer>
				</dict>
			</array>
		</dict>
	</array>
</dict>
</plist>
